petroeval/__init__.py
petroeval/evaluate_reservoir.py
petroeval/files_reader.py
petroeval/plots.py
petroeval/preprocessing.py
petroeval/pseudomodes.py
petroeval/utils.py
petroeval/visualizations.py
petroeval/model/eormation_encoded
petroeval/model/group_encoded
petroeval/model/lithofacies_model1.model
petroeval/model/lithofacies_model2.model
petroeval-1.1.5.4.dist-info/LICENSE
petroeval-1.1.5.4.dist-info/METADATA
petroeval-1.1.5.4.dist-info/WHEEL
petroeval-1.1.5.4.dist-info/top_level.txt
petroeval-1.1.5.4.dist-info/RECORD
