Metadata-Version: 2.1
Name: petroeval
Version: 1.1.5.4
Summary: UNKNOWN
Home-page: https://github.com/olawaleibrahim/petroeval
Author: Ibrahim Olawale
Author-email: ibrahim.olawale13@gmail.com
License: UNKNOWN
Platform: UNKNOWN
Classifier: Programming Language :: Python :: 3
Classifier: License :: OSI Approved :: MIT License
Classifier: Operating System :: OS Independent
Requires-Python: >=3.5
Requires-Dist: matplotlib
Requires-Dist: pandas
Requires-Dist: numpy
Requires-Dist: lasio (==0.28)
Requires-Dist: xgboost
Requires-Dist: lightgbm
